Workbook
Name TaxRate: Assumptions!$B$1

Sheet Sales
A1: Region | B1: Product | C1: Units | D1: Unit Price | E1: Discount | F1: Revenue | G1: Tax | H1: Tier | I1: Share | J1: Region Revenue | K1: Region Share | L1: Label | M1: Margin | N1: Code | O1: Region Product Units | P1: List Price | Q1: Running Total
A2: North | B2: Gadget | C2: 25 | D2: 41.81 | F2: =C2*D2*(1-E2) | G2: =F2*TaxRate | H2: =IF(F2>=Assumptions!$B$2,"High",IF(F2>=Assumptions!$B$2/5,"Mid","Low")) | I2: =F2/SUM($F$2:$F$201) | J2: =SUMIF($A$2:$A$201,A2,$F$2:$F$201) | K2: =F2/J2 | L2: =A2&"-"&B2&" x"&C2 | M2: =IFERROR(ROUND((F2-G2)/F2,4),0) | N2: =UPPER(LEFT(B2,3))&MOD(C2,7) | O2: =SUMIFS($C$2:$C$201,$A$2:$A$201,A2,$B$2:$B$201,B2) | P2: =VLOOKUP(B2,Products!$A$2:$B$6,2,FALSE) | Q2: =F2
A3: Central | B3: Widget | C3: 23 | D3: 12.81 | E3: 0.15 | F3: =C3*D3*(1-E3) | G3: =F3*TaxRate | H3: =IF(F3>=Assumptions!$B$2,"High",IF(F3>=Assumptions!$B$2/5,"Mid","Low")) | I3: =F3/SUM($F$2:$F$201) | J3: =SUMIF($A$2:$A$201,A3,$F$2:$F$201) | K3: =F3/J3 | L3: =A3&"-"&B3&" x"&C3 | M3: =IFERROR(ROUND((F3-G3)/F3,4),0) | N3: =UPPER(LEFT(B3,3))&MOD(C3,7) | O3: =SUMIFS($C$2:$C$201,$A$2:$A$201,A3,$B$2:$B$201,B3) | P3: =VLOOKUP(B3,Products!$A$2:$B$6,2,FALSE) | Q3: =Q2+F3
A4: West | B4: Widget | C4: 5 | D4: 12.25 | F4: =C4*D4*(1-E4) | G4: =F4*TaxRate | H4: =IF(F4>=Assumptions!$B$2,"High",IF(F4>=Assumptions!$B$2/5,"Mid","Low")) | I4: =F4/SUM($F$2:$F$201) | J4: =SUMIF($A$2:$A$201,A4,$F$2:$F$201) | K4: =F4/J4 | L4: =A4&"-"&B4&" x"&C4 | M4: =IFERROR(ROUND((F4-G4)/F4,4),0) | N4: =UPPER(LEFT(B4,3))&MOD(C4,7) | O4: =SUMIFS($C$2:$C$201,$A$2:$A$201,A4,$B$2:$B$201,B4) | P4: =VLOOKUP(B4,Products!$A$2:$B$6,2,FALSE) | Q4: =Q3+F4
A5: West | B5: Widget | C5: 35 | D5: 12.22 | E5: 0.15 | F5: =C5*D5*(1-E5) | G5: =F5*TaxRate | H5: =IF(F5>=Assumptions!$B$2,"High",IF(F5>=Assumptions!$B$2/5,"Mid","Low")) | I5: =F5/SUM($F$2:$F$201) | J5: =SUMIF($A$2:$A$201,A5,$F$2:$F$201) | K5: =F5/J5 | L5: =A5&"-"&B5&" x"&C5 | M5: =IFERROR(ROUND((F5-G5)/F5,4),0) | N5: =UPPER(LEFT(B5,3))&MOD(C5,7) | O5: =SUMIFS($C$2:$C$201,$A$2:$A$201,A5,$B$2:$B$201,B5) | P5: =VLOOKUP(B5,Products!$A$2:$B$6,2,FALSE) | Q5: =Q4+F5
A6: East | B6: Gadget | C6: 40 | D6: 41.53 | F6: =C6*D6*(1-E6) | G6: =F6*TaxRate | H6: =IF(F6>=Assumptions!$B$2,"High",IF(F6>=Assumptions!$B$2/5,"Mid","Low")) | I6: =F6/SUM($F$2:$F$201) | J6: =SUMIF($A$2:$A$201,A6,$F$2:$F$201) | K6: =F6/J6 | L6: =A6&"-"&B6&" x"&C6 | M6: =IFERROR(ROUND((F6-G6)/F6,4),0) | N6: =UPPER(LEFT(B6,3))&MOD(C6,7) | O6: =SUMIFS($C$2:$C$201,$A$2:$A$201,A6,$B$2:$B$201,B6) | P6: =VLOOKUP(B6,Products!$A$2:$B$6,2,FALSE) | Q6: =Q5+F6
A7: Central | B7: Sprocket | C7: 25 | D7: 2.68 | E7: 0 | F7: =C7*D7*(1-E7) | G7: =F7*TaxRate | H7: =IF(F7>=Assumptions!$B$2,"High",IF(F7>=Assumptions!$B$2/5,"Mid","Low")) | I7: =F7/SUM($F$2:$F$201) | J7: =SUMIF($A$2:$A$201,A7,$F$2:$F$201) | K7: =F7/J7 | L7: =A7&"-"&B7&" x"&C7 | M7: =IFERROR(ROUND((F7-G7)/F7,4),0) | N7: =UPPER(LEFT(B7,3))&MOD(C7,7) | O7: =SUMIFS($C$2:$C$201,$A$2:$A$201,A7,$B$2:$B$201,B7) | P7: =VLOOKUP(B7,Products!$A$2:$B$6,2,FALSE) | Q7: =Q6+F7
A8: East | B8: Sprocket | C8: 54 | D8: 2.76 | E8: 0.1 | F8: =C8*D8*(1-E8) | G8: =F8*TaxRate | H8: =IF(F8>=Assumptions!$B$2,"High",IF(F8>=Assumptions!$B$2/5,"Mid","Low")) | I8: =F8/SUM($F$2:$F$201) | J8: =SUMIF($A$2:$A$201,A8,$F$2:$F$201) | K8: =F8/J8 | L8: =A8&"-"&B8&" x"&C8 | M8: =IFERROR(ROUND((F8-G8)/F8,4),0) | N8: =UPPER(LEFT(B8,3))&MOD(C8,7) | O8: =SUMIFS($C$2:$C$201,$A$2:$A$201,A8,$B$2:$B$201,B8) | P8: =VLOOKUP(B8,Products!$A$2:$B$6,2,FALSE) | Q8: =Q7+F8
A9: West | B9: Sprocket | C9: 7 | D9: 3.17 | E9: 0.15 | F9: =C9*D9*(1-E9) | G9: 12.5 | H9: =IF(F9>=Assumptions!$B$2,"High",IF(F9>=Assumptions!$B$2/5,"Mid","Low")) | I9: =F9/SUM($F$2:$F$201) | J9: =SUMIF($A$2:$A$201,A9,$F$2:$F$201) | K9: =F9/J9 | L9: =A9&"-"&B9&" x"&C9 | M9: =IFERROR(ROUND((F9-G9)/F9,4),0) | N9: =UPPER(LEFT(B9,3))&MOD(C9,7) | O9: =SUMIFS($C$2:$C$201,$A$2:$A$201,A9,$B$2:$B$201,B9) | P9: =VLOOKUP(B9,Products!$A$2:$B$6,2,FALSE) | Q9: =Q8+F9
A10: West | B10: Widget | C10: 37 | D10: 12.77 | E10: 0 | F10: =C10*D10*(1-E10) | G10: =F10*TaxRate | H10: =IF(F10>=Assumptions!$B$2,"High",IF(F10>=Assumptions!$B$2/5,"Mid","Low")) | I10: =F10/SUM($F$2:$F$201) | J10: =SUMIF($A$2:$A$201,A10,$F$2:$F$201) | K10: =F10/J10 | L10: =A10&"-"&B10&" x"&C10 | M10: =IFERROR(ROUND((F10-G10)/F10,4),0) | N10: =UPPER(LEFT(B10,3))&MOD(C10,7) | O10: =SUMIFS($C$2:$C$201,$A$2:$A$201,A10,$B$2:$B$201,B10) | P10: =VLOOKUP(B10,Products!$A$2:$B$6,2,FALSE) | Q10: =Q9+F10
A11: North | B11: Widget | C11: 35 | D11: 13.3 | E11: 0.15 | F11: =C11*D11*(1-E11) | G11: =F11*TaxRate | H11: =IF(F11>=Assumptions!$B$2,"High",IF(F11>=Assumptions!$B$2/5,"Mid","Low")) | I11: =F11/SUM($F$2:$F$201) | J11: =SUMIF($A$2:$A$201,A11,$F$2:$F$201) | K11: =F11/J11 | L11: =A11&"-"&B11&" x"&C11 | M11: =IFERROR(ROUND((F11-G11)/F11,4),0) | N11: =UPPER(LEFT(B11,3))&MOD(C11,7) | O11: =SUMIFS($C$2:$C$201,$A$2:$A$201,A11,$B$2:$B$201,B11) | P11: =VLOOKUP(B11,Products!$A$2:$B$6,2,FALSE) | Q11: =Q10+F11
A12: East | B12: Sprocket | C12: 13 | D12: 3.1 | E12: 0.15 | F12: =C12*D12*(1-E12) | G12: =F12*TaxRate | H12: =IF(F12>=Assumptions!$B$2,"High",IF(F12>=Assumptions!$B$2/5,"Mid","Low")) | I12: =F12/SUM($F$2:$F$201) | J12: =SUMIF($A$2:$A$201,A12,$F$2:$F$201) | K12: =F12/J12 | L12: =A12&"-"&B12&" x"&C12 | M12: =IFERROR(ROUND((F12-G12)/F12,4),0) | N12: =UPPER(LEFT(B12,3))&MOD(C12,7) | O12: =SUMIFS($C$2:$C$201,$A$2:$A$201,A12,$B$2:$B$201,B12) | P12: =VLOOKUP(B12,Products!$A$2:$B$6,2,FALSE) | Q12: =Q11+F12
A13: South | B13: Gizmo | C13: 29 | D13: 7.44 | E13: 0.1 | F13: =C13*D13*(1-E13) | G13: =F13*TaxRate | H13: =IF(F13>=Assumptions!$B$2,"High",IF(F13>=Assumptions!$B$2/5,"Mid","Low")) | I13: =F13/SUM($F$2:$F$201) | J13: =SUMIF($A$2:$A$201,A13,$F$2:$F$201) | K13: =F13/J13 | L13: =A13&"-"&B13&" x"&C13 | M13: =IFERROR(ROUND((F13-G13)/F13,4),0) | N13: =UPPER(LEFT(B13,3))&MOD(C13,7) | O13: =SUMIFS($C$2:$C$201,$A$2:$A$201,A13,$B$2:$B$201,B13) | P13: =VLOOKUP(B13,Products!$A$2:$B$6,2,FALSE) | Q13: =Q12+F13
A14: North | B14: Gizmo | C14: 15 | D14: 7.89 | E14: 0 | F14: =C14*D14*(1-E14) | G14: =F14*TaxRate | H14: =IF(F14>=Assumptions!$B$2,"High",IF(F14>=Assumptions!$B$2/5,"Mid","Low")) | I14: =F14/SUM($F$2:$F$201) | J14: =SUMIF($A$2:$A$201,A14,$F$2:$F$201) | K14: =F14/J14 | L14: =A14&"-"&B14&" x"&C14 | M14: =IFERROR(ROUND((F14-G14)/F14,4),0) | N14: =UPPER(LEFT(B14,3))&MOD(C14,7) | O14: =SUMIFS($C$2:$C$201,$A$2:$A$201,A14,$B$2:$B$201,B14) | P14: =VLOOKUP(B14,Products!$A$2:$B$6,2,FALSE) | Q14: =Q13+F14
A15: East | B15: Sprocket | C15: 19 | D15: 3.12 | E15: 0.05 | F15: =C15*D15*(1-E15) | G15: =F15*TaxRate | H15: =IF(F15>=Assumptions!$B$2,"High",IF(F15>=Assumptions!$B$2/5,"Mid","Low")) | I15: =F15/SUM($F$2:$F$201) | J15: =SUMIF($A$2:$A$201,A15,$F$2:$F$201) | K15: =F15/J15 | L15: =A15&"-"&B15&" x"&C15 | M15: =IFERROR(ROUND((F15-G15)/F15,4),0) | N15: =UPPER(LEFT(B15,3))&MOD(C15,7) | O15: =SUMIFS($C$2:$C$201,$A$2:$A$201,A15,$B$2:$B$201,B15) | P15: =VLOOKUP(B15,Products!$A$2:$B$6,2,FALSE) | Q15: =Q14+F15
A16: South | B16: Gizmo | C16: 38 | D16: 8.29 | F16: =C16*D16*(1-E16) | G16: =F16*TaxRate | H16: =IF(F16>=Assumptions!$B$2,"High",IF(F16>=Assumptions!$B$2/5,"Mid","Low")) | I16: =F16/SUM($F$2:$F$201) | J16: =SUMIF($A$2:$A$201,A16,$F$2:$F$201) | K16: =F16/J16 | L16: =A16&"-"&B16&" x"&C16 | M16: =IFERROR(ROUND((F16-G16)/F16,4),0) | N16: =UPPER(LEFT(B16,3))&MOD(C16,7) | O16: =SUMIFS($C$2:$C$201,$A$2:$A$201,A16,$B$2:$B$201,B16) | P16: =VLOOKUP(B16,Products!$A$2:$B$6,2,FALSE) | Q16: =Q15+F16
A17: Central | B17: Doohickey | C17: 10 | D17: 106.64 | E17: 0 | F17: =C17*D17*(1-E17) | G17: =F17*TaxRate | H17: =IF(F17>=Assumptions!$B$2,"High",IF(F17>=Assumptions!$B$2/5,"Mid","Low")) | I17: =F17/SUM($F$2:$F$201) | J17: =SUMIF($A$2:$A$201,A17,$F$2:$F$201) | K17: =F17/J17 | L17: =A17&"-"&B17&" x"&C17 | M17: =IFERROR(ROUND((F17-G17)/F17,4),0) | N17: =UPPER(LEFT(B17,3))&MOD(C17,7) | O17: =SUMIFS($C$2:$C$201,$A$2:$A$201,A17,$B$2:$B$201,B17) | P17: =VLOOKUP(B17,Products!$A$2:$B$6,2,FALSE) | Q17: =Q16+F17
A18: South | B18: Doohickey | C18: 2 | D18: 112.72 | F18: =C18*D18*(1-E18) | G18: =F18*TaxRate | H18: =IF(F18>=Assumptions!$B$2,"High",IF(F18>=Assumptions!$B$2/5,"Mid","Low")) | I18: =F18/SUM($F$2:$F$201) | J18: =SUMIF($A$2:$A$201,A18,$F$2:$F$201) | K18: =F18/J18 | L18: =A18&"-"&B18&" x"&C18 | M18: =IFERROR(ROUND((F18-G18)/F18,4),0) | N18: =UPPER(LEFT(B18,3))&MOD(C18,7) | O18: =SUMIFS($C$2:$C$201,$A$2:$A$201,A18,$B$2:$B$201,B18) | P18: =VLOOKUP(B18,Products!$A$2:$B$6,2,FALSE) | Q18: =Q17+F18
A19: Central | B19: Sprocket | C19: 50 | D19: 3.45 | E19: 0.05 | F19: =C19*D19*(1-E19) | G19: =F19*TaxRate | H19: =IF(F19>=Assumptions!$B$2,"High",IF(F19>=Assumptions!$B$2/5,"Mid","Low")) | I19: =F19/SUM($F$2:$F$201) | J19: =SUMIF($A$2:$A$201,A19,$F$2:$F$201) | K19: =F19/J19 | L19: =A19&"-"&B19&" x"&C19 | M19: =IFERROR(ROUND((F19-G19)/F19,4),0) | N19: =UPPER(LEFT(B19,3))&MOD(C19,7) | O19: =SUMIFS($C$2:$C$201,$A$2:$A$201,A19,$B$2:$B$201,B19) | P19: =VLOOKUP(B19,Products!$A$2:$B$6,2,FALSE) | Q19: =Q18+F19
A20: North | B20: Gizmo | C20: 38 | D20: 7.24 | E20: 0.1 | F20: =C20*D20*(1-E20) | G20: =F20*TaxRate | H20: =IF(F20>=Assumptions!$B$2,"High",IF(F20>=Assumptions!$B$2/5,"Mid","Low")) | I20: =F20/SUM($F$2:$F$201) | J20: =SUMIF($A$2:$A$201,A20,$F$2:$F$201) | K20: =F20/J20 | L20: =A20&"-"&B20&" x"&C20 | M20: =IFERROR(ROUND((F20-G20)/F20,4),0) | N20: =UPPER(LEFT(B20,3))&MOD(C20,7) | O20: =SUMIFS($C$2:$C$201,$A$2:$A$201,A20,$B$2:$B$201,B20) | P20: =VLOOKUP(B20,Products!$A$2:$B$6,2,FALSE) | Q20: =Q19+F20
A21: East | B21: Widget | C21: 60 | D21: 11.64 | F21: =C21*D21*(1-E21) | G21: =F21*TaxRate | H21: =IF(F21>=Assumptions!$B$2,"High",IF(F21>=Assumptions!$B$2/5,"Mid","Low")) | I21: =F21/SUM($F$2:$F$201) | J21: =SUMIF($A$2:$A$201,A21,$F$2:$F$201) | K21: =F21/J21 | L21: =A21&"-"&B21&" x"&C21 | M21: =IFERROR(ROUND((F21-G21)/F21,4),0) | N21: =UPPER(LEFT(B21,3))&MOD(C21,7) | O21: =SUMIFS($C$2:$C$201,$A$2:$A$201,A21,$B$2:$B$201,B21) | P21: =VLOOKUP(B21,Products!$A$2:$B$6,2,FALSE) | Q21: =Q20+F21
A22: East | B22: Gizmo | C22: 41 | D22: 7.42 | E22: 0.1 | F22: =C22*D22*(1-E22) | G22: =F22*TaxRate | H22: =IF(F22>=Assumptions!$B$2,"High",IF(F22>=Assumptions!$B$2/5,"Mid","Low")) | I22: =F22/SUM($F$2:$F$201) | J22: =SUMIF($A$2:$A$201,A22,$F$2:$F$201) | K22: =F22/J22 | L22: =A22&"-"&B22&" x"&C22 | M22: =IFERROR(ROUND((F22-G22)/F22,4),0) | N22: =UPPER(LEFT(B22,3))&MOD(C22,7) | O22: =SUMIFS($C$2:$C$201,$A$2:$A$201,A22,$B$2:$B$201,B22) | P22: =VLOOKUP(B22,Products!$A$2:$B$6,2,FALSE) | Q22: =Q21+F22
A23: North | B23: Doohickey | C23: 56 | D23: 104.01 | F23: =C23*D23*(1-E23) | G23: =F23*TaxRate | H23: =IF(F23>=Assumptions!$B$2,"High",IF(F23>=Assumptions!$B$2/5,"Mid","Low")) | I23: =F23/SUM($F$2:$F$201) | J23: =SUMIF($A$2:$A$201,A23,$F$2:$F$201) | K23: =F23/J23 | L23: =A23&"-"&B23&" x"&C23 | M23: =IFERROR(ROUND((F23-G23)/F23,4),0) | N23: =UPPER(LEFT(B23,3))&MOD(C23,7) | O23: =SUMIFS($C$2:$C$201,$A$2:$A$201,A23,$B$2:$B$201,B23) | P23: =VLOOKUP(B23,Products!$A$2:$B$6,2,FALSE) | Q23: =Q22+F23
A24: South | B24: Gizmo | C24: 10 | D24: 7.49 | E24: 0.1 | F24: =C24*D24*(1-E24) | G24: =F24*TaxRate | H24: =IF(F24>=Assumptions!$B$2,"High",IF(F24>=Assumptions!$B$2/5,"Mid","Low")) | I24: =F24/SUM($F$2:$F$201) | J24: =SUMIF($A$2:$A$201,A24,$F$2:$F$201) | K24: =F24/J24 | L24: =A24&"-"&B24&" x"&C24 | M24: =IFERROR(ROUND((F24-G24)/F24,4),0) | N24: =UPPER(LEFT(B24,3))&MOD(C24,7) | O24: =SUMIFS($C$2:$C$201,$A$2:$A$201,A24,$B$2:$B$201,B24) | P24: =VLOOKUP(B24,Products!$A$2:$B$6,2,FALSE) | Q24: =Q23+F24
A25: East | B25: Gadget | C25: 49 | D25: 37.45 | E25: 0 | F25: =C25*D25*(1-E25) | G25: =F25*TaxRate | H25: =IF(F25>=Assumptions!$B$2,"High",IF(F25>=Assumptions!$B$2/5,"Mid","Low")) | I25: =F25/SUM($F$2:$F$201) | J25: =SUMIF($A$2:$A$201,A25,$F$2:$F$201) | K25: =F25/J25 | L25: =A25&"-"&B25&" x"&C25 | M25: =IFERROR(ROUND((F25-G25)/F25,4),0) | N25: =UPPER(LEFT(B25,3))&MOD(C25,7) | O25: =SUMIFS($C$2:$C$201,$A$2:$A$201,A25,$B$2:$B$201,B25) | P25: =VLOOKUP(B25,Products!$A$2:$B$6,2,FALSE) | Q25: =Q24+F25
A26: South | B26: Doohickey | C26: 58 | D26: 110.03 | F26: =C26*D26*(1-E26) | G26: =F26*TaxRate | H26: =IF(F26>=Assumptions!$B$2,"High",IF(F26>=Assumptions!$B$2/5,"Mid","Low")) | I26: =F26/SUM($F$2:$F$201) | J26: =SUMIF($A$2:$A$201,A26,$F$2:$F$201) | K26: =F26/J26 | L26: =A26&"-"&B26&" x"&C26 | M26: =IFERROR(ROUND((F26-G26)/F26,4),0) | N26: =UPPER(LEFT(B26,3))&MOD(C26,7) | O26: =SUMIFS($C$2:$C$201,$A$2:$A$201,A26,$B$2:$B$201,B26) | P26: =VLOOKUP(B26,Products!$A$2:$B$6,2,FALSE) | Q26: =Q25+F26
A27: West | B27: Doohickey | C27: 25 | D27: 100.47 | E27: 0 | F27: =C27*D27*(1-E27) | G27: =F27*TaxRate | H27: =IF(F27>=Assumptions!$B$2,"High",IF(F27>=Assumptions!$B$2/5,"Mid","Low")) | I27: =F27/SUM($F$2:$F$201) | J27: =SUMIF($A$2:$A$201,A27,$F$2:$F$201) | K27: =F27/J27 | L27: =A27&"-"&B27&" x"&C27 | M27: =IFERROR(ROUND((F27-G27)/F27,4),0) | N27: =UPPER(LEFT(B27,3))&MOD(C27,7) | O27: =SUMIFS($C$2:$C$201,$A$2:$A$201,A27,$B$2:$B$201,B27) | P27: =VLOOKUP(B27,Products!$A$2:$B$6,2,FALSE) | Q27: =Q26+F27
A28: South | B28: Sprocket | C28: 17 | D28: 3.29 | E28: 0.05 | F28: =C28*D28*(1-E28) | G28: =F28*TaxRate | H28: =IF(F28>=Assumptions!$B$2,"High",IF(F28>=Assumptions!$B$2/5,"Mid","Low")) | I28: =F28/SUM($F$2:$F$201) | J28: =SUMIF($A$2:$A$201,A28,$F$2:$F$201) | K28: =F28/J28 | L28: =A28&"-"&B28&" x"&C28 | M28: =IFERROR(ROUND((F28-G28)/F28,4),0) | N28: =UPPER(LEFT(B28,3))&MOD(C28,7) | O28: =SUMIFS($C$2:$C$201,$A$2:$A$201,A28,$B$2:$B$201,B28) | P28: =VLOOKUP(B28,Products!$A$2:$B$6,2,FALSE) | Q28: =Q27+F28
A29: South | B29: Gadget | C29: 9 | D29: 35 | E29: 0 | F29: =C29*D29*(1-E29) | G29: =F29*TaxRate | H29: =IF(F29>=Assumptions!$B$2,"High",IF(F29>=Assumptions!$B$2/5,"Mid","Low")) | I29: =F29/SUM($F$2:$F$201) | J29: =SUMIF($A$2:$A$201,A29,$F$2:$F$201) | K29: =F29/J29 | L29: =A29&"-"&B29&" x"&C29 | M29: =IFERROR(ROUND((F29-G29)/F29,4),0) | N29: =UPPER(LEFT(B29,3))&MOD(C29,7) | O29: =SUMIFS($C$2:$C$201,$A$2:$A$201,A29,$B$2:$B$201,B29) | P29: =VLOOKUP(B29,Products!$A$2:$B$6,2,FALSE) | Q29: =Q28+F29
A30: West | B30: Gadget | C30: 0 | D30: 39.82 | E30: 0.15 | F30: =C30*D30*(1-E30) | G30: =F30*TaxRate | H30: =IF(F30>=Assumptions!$B$2,"High",IF(F30>=Assumptions!$B$2/5,"Mid","Low")) | I30: =F30/SUM($F$2:$F$201) | J30: =SUMIF($A$2:$A$201,A30,$F$2:$F$201) | K30: =F30/J30 | L30: =A30&"-"&B30&" x"&C30 | M30: =IFERROR(ROUND((F30-G30)/F30,4),0) | N30: =UPPER(LEFT(B30,3))&MOD(C30,7) | O30: =SUMIFS($C$2:$C$201,$A$2:$A$201,A30,$B$2:$B$201,B30) | P30: =VLOOKUP(B30,Products!$A$2:$B$6,2,FALSE) | Q30: =Q29+F30
A31: West | B31: Gizmo | C31: 18 | D31: 6.17 | E31: 0.1 | F31: =C31*D31*(1-E31) | G31: =F31*TaxRate | H31: =IF(F31>=Assumptions!$B$2,"High",IF(F31>=Assumptions!$B$2/5,"Mid","Low")) | I31: =F31/SUM($F$2:$F$201) | J31: =SUMIF($A$2:$A$201,A31,$F$2:$F$201) | K31: =F31/J31 | L31: =A31&"-"&B31&" x"&C31 | M31: =IFERROR(ROUND((F31-G31)/F31,4),0) | N31: =UPPER(LEFT(B31,3))&MOD(C31,7) | O31: =SUMIFS($C$2:$C$201,$A$2:$A$201,A31,$B$2:$B$201,B31) | P31: =VLOOKUP(B31,Products!$A$2:$B$6,2,FALSE) | Q31: =Q30+F31
A32: Central | B32: Gizmo | C32: 39 | D32: 7.39 | E32: 0 | F32: =C32*D32*(1-E32) | G32: =F32*TaxRate | H32: =IF(F32>=Assumptions!$B$2,"High",IF(F32>=Assumptions!$B$2/5,"Mid","Low")) | I32: =F32/SUM($F$2:$F$201) | J32: =SUMIF($A$2:$A$201,A32,$F$2:$F$201) | K32: =F32/J32 | L32: =A32&"-"&B32&" x"&C32 | M32: =IFERROR(ROUND((F32-G32)/F32,4),0) | N32: =UPPER(LEFT(B32,3))&MOD(C32,7) | O32: =SUMIFS($C$2:$C$201,$A$2:$A$201,A32,$B$2:$B$201,B32) | P32: =VLOOKUP(B32,Products!$A$2:$B$6,2,FALSE) | Q32: =Q31+F32
A33: Central | B33: Sprocket | C33: 41 | D33: 3.26 | F33: =C33*D33*(1-E33) | G33: =F33*TaxRate | H33: =IF(F33>=Assumptions!$B$2,"High",IF(F33>=Assumptions!$B$2/5,"Mid","Low")) | I33: =F33/SUM($F$2:$F$201) | J33: =SUMIF($A$2:$A$201,A33,$F$2:$F$201) | K33: =F33/J33 | L33: =A33&"-"&B33&" x"&C33 | M33: =IFERROR(ROUND((F33-G33)/F33,4),0) | N33: =UPPER(LEFT(B33,3))&MOD(C33,7) | O33: =SUMIFS($C$2:$C$201,$A$2:$A$201,A33,$B$2:$B$201,B33) | P33: =VLOOKUP(B33,Products!$A$2:$B$6,2,FALSE) | Q33: =Q32+F33
A34: South | B34: Sprocket | C34: 25 | D34: 3.01 | E34: 0.1 | F34: =C34*D34*(1-E34) | G34: =F34*TaxRate | H34: =IF(F34>=Assumptions!$B$2,"High",IF(F34>=Assumptions!$B$2/5,"Mid","Low")) | I34: =F34/SUM($F$2:$F$201) | J34: =SUMIF($A$2:$A$201,A34,$F$2:$F$201) | K34: =F34/J34 | L34: =A34&"-"&B34&" x"&C34 | M34: =IFERROR(ROUND((F34-G34)/F34,4),0) | N34: =UPPER(LEFT(B34,3))&MOD(C34,7) | O34: =SUMIFS($C$2:$C$201,$A$2:$A$201,A34,$B$2:$B$201,B34) | P34: =VLOOKUP(B34,Products!$A$2:$B$6,2,FALSE) | Q34: =Q33+F34
A35: East | B35: Doohickey | C35: 40 | D35: 96.04 | E35: 0 | F35: =C35*D35*(1-E35) | G35: =F35*TaxRate | H35: =IF(F35>=Assumptions!$B$2,"High",IF(F35>=Assumptions!$B$2/5,"Mid","Low")) | I35: =F35/SUM($F$2:$F$201) | J35: =SUMIF($A$2:$A$201,A35,$F$2:$F$201) | K35: =F35/J35 | L35: =A35&"-"&B35&" x"&C35 | M35: =IFERROR(ROUND((F35-G35)/F35,4),0) | N35: =UPPER(LEFT(B35,3))&MOD(C35,7) | O35: =SUMIFS($C$2:$C$201,$A$2:$A$201,A35,$B$2:$B$201,B35) | P35: =VLOOKUP(B35,Products!$A$2:$B$6,2,FALSE) | Q35: =Q34+F35
A36: East | B36: Gadget | C36: 28 | D36: 35.95 | E36: 0.05 | F36: =C36*D36*(1-E36) | G36: =F36*TaxRate | H36: =IF(F36>=Assumptions!$B$2,"High",IF(F36>=Assumptions!$B$2/5,"Mid","Low")) | I36: =F36/SUM($F$2:$F$201) | J36: =SUMIF($A$2:$A$201,A36,$F$2:$F$201) | K36: =F36/J36 | L36: =A36&"-"&B36&" x"&C36 | M36: =IFERROR(ROUND((F36-G36)/F36,4),0) | N36: =UPPER(LEFT(B36,3))&MOD(C36,7) | O36: =SUMIFS($C$2:$C$201,$A$2:$A$201,A36,$B$2:$B$201,B36) | P36: =VLOOKUP(B36,Products!$A$2:$B$6,2,FALSE) | Q36: =Q35+F36
A37: Central | B37: Widget | C37: 6 | D37: 10.63 | E37: 0 | F37: =C37*D37*(1-E37) | G37: =F37*TaxRate | H37: =IF(F37>=Assumptions!$B$2,"High",IF(F37>=Assumptions!$B$2/5,"Mid","Low")) | I37: =F37/SUM($F$2:$F$201) | J37: =SUMIF($A$2:$A$201,A37,$F$2:$F$201) | K37: =F37/J37 | L37: =A37&"-"&B37&" x"&C37 | M37: =IFERROR(ROUND((F37-G37)/F37,4),0) | N37: =UPPER(LEFT(B37,3))&MOD(C37,7) | O37: =SUMIFS($C$2:$C$201,$A$2:$A$201,A37,$B$2:$B$201,B37) | P37: =VLOOKUP(B37,Products!$A$2:$B$6,2,FALSE) | Q37: =Q36+F37
A38: Central | B38: Widget | C38: 60 | D38: 11.99 | F38: =C38*D38*(1-E38) | G38: =F38*TaxRate | H38: =IF(F38>=Assumptions!$B$2,"High",IF(F38>=Assumptions!$B$2/5,"Mid","Low")) | I38: =F38/SUM($F$2:$F$201) | J38: =SUMIF($A$2:$A$201,A38,$F$2:$F$201) | K38: =F38/J38 | L38: =A38&"-"&B38&" x"&C38 | M38: =IFERROR(ROUND((F38-G38)/F38,4),0) | N38: =UPPER(LEFT(B38,3))&MOD(C38,7) | O38: =SUMIFS($C$2:$C$201,$A$2:$A$201,A38,$B$2:$B$201,B38) | P38: =VLOOKUP(B38,Products!$A$2:$B$6,2,FALSE) | Q38: =Q37+F38
A39: East | B39: Gadget | C39: 39 | D39: 38.51 | E39: 0.05 | F39: =C39*D39*(1-E39) | G39: =F39*TaxRate | H39: =IF(F39>=Assumptions!$B$2,"High",IF(F39>=Assumptions!$B$2/5,"Mid","Low")) | I39: =F39/SUM($F$2:$F$201) | J39: =SUMIF($A$2:$A$201,A39,$F$2:$F$201) | K39: =F39/J39 | L39: =A39&"-"&B39&" x"&C39 | M39: =IFERROR(ROUND((F39-G39)/F39,4),0) | N39: =UPPER(LEFT(B39,3))&MOD(C39,7) | O39: =SUMIFS($C$2:$C$201,$A$2:$A$201,A39,$B$2:$B$201,B39) | P39: =VLOOKUP(B39,Products!$A$2:$B$6,2,FALSE) | Q39: =Q38+F39
A40: North | B40: Sprocket | C40: 23 | D40: 3.08 | F40: =C40*D40*(1-E40) | G40: =F40*TaxRate | H40: =IF(F40>=Assumptions!$B$2,"High",IF(F40>=Assumptions!$B$2/5,"Mid","Low")) | I40: =F40/SUM($F$2:$F$201) | J40: =SUMIF($A$2:$A$201,A40,$F$2:$F$201) | K40: =F40/J40 | L40: =A40&"-"&B40&" x"&C40 | M40: =IFERROR(ROUND((F40-G40)/F40,4),0) | N40: =UPPER(LEFT(B40,3))&MOD(C40,7) | O40: =SUMIFS($C$2:$C$201,$A$2:$A$201,A40,$B$2:$B$201,B40) | P40: =VLOOKUP(B40,Products!$A$2:$B$6,2,FALSE) | Q40: =Q39+F40
A41: South | B41: Doohickey | C41: 30 | D41: 98.52 | F41: =C41*D41*(1-E41) | G41: =F41*TaxRate | H41: =IF(F41>=Assumptions!$B$2,"High",IF(F41>=Assumptions!$B$2/5,"Mid","Low")) | I41: =F41/SUM($F$2:$F$201) | J41: =SUMIF($A$2:$A$201,A41,$F$2:$F$201) | K41: =F41/J41 | L41: =A41&"-"&B41&" x"&C41 | M41: =IFERROR(ROUND((F41-G41)/F41,4),0) | N41: =UPPER(LEFT(B41,3))&MOD(C41,7) | O41: =SUMIFS($C$2:$C$201,$A$2:$A$201,A41,$B$2:$B$201,B41) | P41: =VLOOKUP(B41,Products!$A$2:$B$6,2,FALSE) | Q41: =Q40+F41
A42: West | B42: Widget | C42: 47 | D42: 11.91 | E42: 0.05 | F42: =C42*D42*(1-E42) | G42: =F42*TaxRate | H42: =IF(F42>=Assumptions!$B$2,"High",IF(F42>=Assumptions!$B$2/5,"Mid","Low")) | I42: =F42/SUM($F$2:$F$201) | J42: =SUMIF($A$2:$A$201,A42,$F$2:$F$201) | K42: =F42/J42 | L42: =A42&"-"&B42&" x"&C42 | M42: =IFERROR(ROUND((F42-G42)/F42,4),0) | N42: =UPPER(LEFT(B42,3))&MOD(C42,7) | O42: =SUMIFS($C$2:$C$201,$A$2:$A$201,A42,$B$2:$B$201,B42) | P42: =VLOOKUP(B42,Products!$A$2:$B$6,2,FALSE) | Q42: =Q41+F42
A43: South | B43: Gadget | C43: 33 | D43: 34.28 | E43: 0.15 | F43: =C43*D43*(1-E43) | G43: =F43*TaxRate | H43: =IF(F43>=Assumptions!$B$2,"High",IF(F43>=Assumptions!$B$2/5,"Mid","Low")) | I43: =F43/SUM($F$2:$F$201) | J43: =SUMIF($A$2:$A$201,A43,$F$2:$F$201) | K43: =F43/J43 | L43: =A43&"-"&B43&" x"&C43 | M43: =IFERROR(ROUND((F43-G43)/F43,4),0) | N43: =UPPER(LEFT(B43,3))&MOD(C43,7) | O43: =SUMIFS($C$2:$C$201,$A$2:$A$201,A43,$B$2:$B$201,B43) | P43: =VLOOKUP(B43,Products!$A$2:$B$6,2,FALSE) | Q43: =Q42+F43
A44: North | B44: Gadget | C44: 44 | D44: 40.52 | F44: =C44*D44*(1-E44) | G44: =F44*TaxRate | H44: =IF(F44>=Assumptions!$B$2,"High",IF(F44>=Assumptions!$B$2/5,"Mid","Low")) | I44: =F44/SUM($F$2:$F$201) | J44: =SUMIF($A$2:$A$201,A44,$F$2:$F$201) | K44: =F44/J44 | L44: =A44&"-"&B44&" x"&C44 | M44: =IFERROR(ROUND((F44-G44)/F44,4),0) | N44: =UPPER(LEFT(B44,3))&MOD(C44,7) | O44: =SUMIFS($C$2:$C$201,$A$2:$A$201,A44,$B$2:$B$201,B44) | P44: =VLOOKUP(B44,Products!$A$2:$B$6,2,FALSE) | Q44: =Q43+F44
A45: Central | B45: Gizmo | C45: 41 | D45: 8.04 | E45: 0.05 | F45: =C45*D45*(1-E45) | G45: =F45*TaxRate | H45: =IF(F45>=Assumptions!$B$2,"High",IF(F45>=Assumptions!$B$2/5,"Mid","Low")) | I45: =F45/SUM($F$2:$F$201) | J45: =SUMIF($A$2:$A$201,A45,$F$2:$F$201) | K45: =F45/J45 | L45: =A45&"-"&B45&" x"&C45 | M45: =IFERROR(ROUND((F45-G45)/F45,4),0) | N45: =UPPER(LEFT(B45,3))&MOD(C45,7) | O45: =SUMIFS($C$2:$C$201,$A$2:$A$201,A45,$B$2:$B$201,B45) | P45: =VLOOKUP(B45,Products!$A$2:$B$6,2,FALSE) | Q45: =Q44+F45
A46: Central | B46: Gizmo | C46: 58 | D46: 6.53 | E46: 0 | F46: =C46*D46*(1-E46) | G46: =F46*TaxRate | H46: =IF(F46>=Assumptions!$B$2,"High",IF(F46>=Assumptions!$B$2/5,"Mid","Low")) | I46: =F46/SUM($F$2:$F$201) | J46: =SUMIF($A$2:$A$201,A46,$F$2:$F$201) | K46: =F46/J46 | L46: =A46&"-"&B46&" x"&C46 | M46: =IFERROR(ROUND((F46-G46)/F46,4),0) | N46: =UPPER(LEFT(B46,3))&MOD(C46,7) | O46: =SUMIFS($C$2:$C$201,$A$2:$A$201,A46,$B$2:$B$201,B46) | P46: =VLOOKUP(B46,Products!$A$2:$B$6,2,FALSE) | Q46: =Q45+F46
A47: Central | B47: Sprocket | C47: 49 | D47: 3.1 | E47: 0 | F47: =C47*D47*(1-E47) | G47: =F47*TaxRate | H47: =IF(F47>=Assumptions!$B$2,"High",IF(F47>=Assumptions!$B$2/5,"Mid","Low")) | I47: =F47/SUM($F$2:$F$201) | J47: =SUMIF($A$2:$A$201,A47,$F$2:$F$201) | K47: =F47/J47 | L47: =A47&"-"&B47&" x"&C47 | M47: =IFERROR(ROUND((F47-G47)/F47,4),0) | N47: =UPPER(LEFT(B47,3))&MOD(C47,7) | O47: =SUMIFS($C$2:$C$201,$A$2:$A$201,A47,$B$2:$B$201,B47) | P47: =VLOOKUP(B47,Products!$A$2:$B$6,2,FALSE) | Q47: =Q46+F47
A48: Central | B48: Gadget | C48: 51 | D48: 36.87 | E48: 0.1 | F48: =C48*D48*(1-E48) | G48: =F48*TaxRate | H48: =IF(F48>=Assumptions!$B$2,"High",IF(F48>=Assumptions!$B$2/5,"Mid","Low")) | I48: =F48/SUM($F$2:$F$201) | J48: =SUMIF($A$2:$A$201,A48,$F$2:$F$201) | K48: =F48/J48 | L48: =A48&"-"&B48&" x"&C48 | M48: =IFERROR(ROUND((F48-G48)/F48,4),0) | N48: =UPPER(LEFT(B48,3))&MOD(C48,7) | O48: =SUMIFS($C$2:$C$201,$A$2:$A$201,A48,$B$2:$B$201,B48) | P48: =VLOOKUP(B48,Products!$A$2:$B$6,2,FALSE) | Q48: =Q47+F48
A49: West | B49: Gadget | C49: 33 | D49: 39.91 | F49: =C49*D49*(1-E49) | G49: =F49*TaxRate | H49: =IF(F49>=Assumptions!$B$2,"High",IF(F49>=Assumptions!$B$2/5,"Mid","Low")) | I49: =F49/SUM($F$2:$F$201) | J49: =SUMIF($A$2:$A$201,A49,$F$2:$F$201) | K49: =F49/J49 | L49: =A49&"-"&B49&" x"&C49 | M49: =IFERROR(ROUND((F49-G49)/F49,4),0) | N49: =UPPER(LEFT(B49,3))&MOD(C49,7) | O49: =SUMIFS($C$2:$C$201,$A$2:$A$201,A49,$B$2:$B$201,B49) | P49: =VLOOKUP(B49,Products!$A$2:$B$6,2,FALSE) | Q49: =Q48+F49
A50: East | B50: Gizmo | C50: 30 | D50: 6.73 | E50: 0.15 | F50: =C50*D50*(1-E50) | G50: =F50*TaxRate | H50: =IF(F50>=Assumptions!$B$2,"High",IF(F50>=Assumptions!$B$2/5,"Mid","Low")) | I50: =F50/SUM($F$2:$F$201) | J50: =SUMIF($A$2:$A$201,A50,$F$2:$F$201) | K50: =F50/J50 | L50: =A50&"-"&B50&" x"&C50 | M50: =IFERROR(ROUND((F50-G50)/F50,4),0) | N50: =UPPER(LEFT(B50,3))&MOD(C50,7) | O50: =SUMIFS($C$2:$C$201,$A$2:$A$201,A50,$B$2:$B$201,B50) | P50: =VLOOKUP(B50,Products!$A$2:$B$6,2,FALSE) | Q50: =Q49+F50
A51: North | B51: Doohickey | C51: 51 | D51: 111.98 | E51: 0.05 | F51: =C51*D51*(1-E51) | G51: =F51*TaxRate | H51: =IF(F51>=Assumptions!$B$2,"High",IF(F51>=Assumptions!$B$2/5,"Mid","Low")) | I51: =F51/SUM($F$2:$F$201) | J51: =SUMIF($A$2:$A$201,A51,$F$2:$F$201) | K51: =F51/J51 | L51: =A51&"-"&B51&" x"&C51 | M51: =IFERROR(ROUND((F51-G51)/F51,4),0) | N51: =UPPER(LEFT(B51,3))&MOD(C51,7) | O51: =SUMIFS($C$2:$C$201,$A$2:$A$201,A51,$B$2:$B$201,B51) | P51: =VLOOKUP(B51,Products!$A$2:$B$6,2,FALSE) | Q51: =Q50+F51
A52: North | B52: Widget | C52: 14 | D52: 11.01 | E52: 0.1 | F52: =C52*D52*(1-E52) | G52: =F52*TaxRate | H52: =IF(F52>=Assumptions!$B$2,"High",IF(F52>=Assumptions!$B$2/5,"Mid","Low")) | I52: =F52/SUM($F$2:$F$201) | J52: =SUMIF($A$2:$A$201,A52,$F$2:$F$201) | K52: =F52/J52 | L52: =A52&"-"&B52&" x"&C52 | M52: =IFERROR(ROUND((F52-G52)/F52,4),0) | N52: =UPPER(LEFT(B52,3))&MOD(C52,7) | O52: =SUMIFS($C$2:$C$201,$A$2:$A$201,A52,$B$2:$B$201,B52) | P52: =VLOOKUP(B52,Products!$A$2:$B$6,2,FALSE) | Q52: =Q51+F52
A53: West | B53: Gizmo | C53: 13 | D53: 7.21 | E53: 0.15 | F53: =C53*D53*(1-E53) | G53: =F53*TaxRate | H53: =IF(F53>=Assumptions!$B$2,"High",IF(F53>=Assumptions!$B$2/5,"Mid","Low")) | I53: =F53/SUM($F$2:$F$201) | J53: =SUMIF($A$2:$A$201,A53,$F$2:$F$201) | K53: =F53/J53 | L53: =A53&"-"&B53&" x"&C53 | M53: =IFERROR(ROUND((F53-G53)/F53,4),0) | N53: =UPPER(LEFT(B53,3))&MOD(C53,7) | O53: =SUMIFS($C$2:$C$201,$A$2:$A$201,A53,$B$2:$B$201,B53) | P53: =VLOOKUP(B53,Products!$A$2:$B$6,2,FALSE) | Q53: =Q52+F53
A54: East | B54: Doohickey | C54: 58 | D54: 103.54 | F54: =C54*D54*(1-E54) | G54: =F54*TaxRate | H54: =IF(F54>=Assumptions!$B$2,"High",IF(F54>=Assumptions!$B$2/5,"Mid","Low")) | I54: =F54/SUM($F$2:$F$201) | J54: =SUMIF($A$2:$A$201,A54,$F$2:$F$201) | K54: =F54/J54 | L54: =A54&"-"&B54&" x"&C54 | M54: =IFERROR(ROUND((F54-G54)/F54,4),0) | N54: =UPPER(LEFT(B54,3))&MOD(C54,7) | O54: =SUMIFS($C$2:$C$201,$A$2:$A$201,A54,$B$2:$B$201,B54) | P54: =VLOOKUP(B54,Products!$A$2:$B$6,2,FALSE) | Q54: =Q53+F54
A55: East | B55: Doohickey | C55: 50 | D55: 105.28 | E55: 0 | F55: =C55*D55*(1-E55) | G55: =F55*TaxRate | H55: =IF(F55>=Assumptions!$B$2,"High",IF(F55>=Assumptions!$B$2/5,"Mid","Low")) | I55: =F55/SUM($F$2:$F$201) | J55: =SUMIF($A$2:$A$201,A55,$F$2:$F$201) | K55: =F55/J55 | L55: =A55&"-"&B55&" x"&C55 | M55: =IFERROR(ROUND((F55-G55)/F55,4),0) | N55: =UPPER(LEFT(B55,3))&MOD(C55,7) | O55: =SUMIFS($C$2:$C$201,$A$2:$A$201,A55,$B$2:$B$201,B55) | P55: =VLOOKUP(B55,Products!$A$2:$B$6,2,FALSE) | Q55: =Q54+F55
A56: South | B56: Gadget | C56: 27 | D56: 43.47 | E56: 0.05 | F56: =C56*D56*(1-E56) | G56: =F56*TaxRate | H56: =IF(F56>=Assumptions!$B$2,"High",IF(F56>=Assumptions!$B$2/5,"Mid","Low")) | I56: =F56/SUM($F$2:$F$201) | J56: =SUMIF($A$2:$A$201,A56,$F$2:$F$201) | K56: =F56/J56 | L56: =A56&"-"&B56&" x"&C56 | M56: =IFERROR(ROUND((F56-G56)/F56,4),0) | N56: =UPPER(LEFT(B56,3))&MOD(C56,7) | O56: =SUMIFS($C$2:$C$201,$A$2:$A$201,A56,$B$2:$B$201,B56) | P56: =VLOOKUP(B56,Products!$A$2:$B$6,2,FALSE) | Q56: =Q55+F56
A57: East | B57: Doohickey | C57: 29 | D57: 96.07 | F57: =C57*D57*(1-E57) | G57: =F57*TaxRate | H57: =IF(F57>=Assumptions!$B$2,"High",IF(F57>=Assumptions!$B$2/5,"Mid","Low")) | I57: =F57/SUM($F$2:$F$201) | J57: =SUMIF($A$2:$A$201,A57,$F$2:$F$201) | K57: =F57/J57 | L57: =A57&"-"&B57&" x"&C57 | M57: =IFERROR(ROUND((F57-G57)/F57,4),0) | N57: =UPPER(LEFT(B57,3))&MOD(C57,7) | O57: =SUMIFS($C$2:$C$201,$A$2:$A$201,A57,$B$2:$B$201,B57) | P57: =VLOOKUP(B57,Products!$A$2:$B$6,2,FALSE) | Q57: =Q56+F57
A58: West | B58: Gadget | C58: 8 | D58: 34.33 | E58: 0.15 | F58: =C58*D58*(1-E58) | G58: =F58*TaxRate | H58: =IF(F58>=Assumptions!$B$2,"High",IF(F58>=Assumptions!$B$2/5,"Mid","Low")) | I58: =F58/SUM($F$2:$F$201) | J58: =SUMIF($A$2:$A$201,A58,$F$2:$F$201) | K58: =F58/J58 | L58: =A58&"-"&B58&" x"&C58 | M58: =IFERROR(ROUND((F58-G58)/F58,4),0) | N58: =UPPER(LEFT(B58,3))&MOD(C58,7) | O58: =SUMIFS($C$2:$C$201,$A$2:$A$201,A58,$B$2:$B$201,B58) | P58: =VLOOKUP(B58,Products!$A$2:$B$6,2,FALSE) | Q58: =Q57+F58
A59: South | B59: Gadget | C59: 39 | D59: 43.92 | E59: 0.1 | F59: =C59*D59*(1-E59) | G59: =F59*TaxRate | H59: =IF(F59>=Assumptions!$B$2,"High",IF(F59>=Assumptions!$B$2/5,"Mid","Low")) | I59: =F59/SUM($F$2:$F$201) | J59: =SUMIF($A$2:$A$201,A59,$F$2:$F$201) | K59: =F59/J59 | L59: =A59&"-"&B59&" x"&C59 | M59: =IFERROR(ROUND((F59-G59)/F59,4),0) | N59: =UPPER(LEFT(B59,3))&MOD(C59,7) | O59: =SUMIFS($C$2:$C$201,$A$2:$A$201,A59,$B$2:$B$201,B59) | P59: =VLOOKUP(B59,Products!$A$2:$B$6,2,FALSE) | Q59: =Q58+F59
A60: North | B60: Gadget | C60: 35 | D60: 40.58 | F60: =C60*D60*(1-E60) | G60: =F60*TaxRate | H60: =IF(F60>=Assumptions!$B$2,"High",IF(F60>=Assumptions!$B$2/5,"Mid","Low")) | I60: =F60/SUM($F$2:$F$201) | J60: =SUMIF($A$2:$A$201,A60,$F$2:$F$201) | K60: =F60/J60 | L60: =A60&"-"&B60&" x"&C60 | M60: =IFERROR(ROUND((F60-G60)/F60,4),0) | N60: =UPPER(LEFT(B60,3))&MOD(C60,7) | O60: =SUMIFS($C$2:$C$201,$A$2:$A$201,A60,$B$2:$B$201,B60) | P60: =VLOOKUP(B60,Products!$A$2:$B$6,2,FALSE) | Q60: =Q59+F60
A61: East | B61: Widget | C61: 33 | D61: 13.44 | E61: 0 | F61: =C61*D61*(1-E61) | G61: =F61*TaxRate | H61: =IF(F61>=Assumptions!$B$2,"High",IF(F61>=Assumptions!$B$2/5,"Mid","Low")) | I61: =F61/SUM($F$2:$F$201) | J61: =SUMIF($A$2:$A$201,A61,$F$2:$F$201) | K61: =F61/J61 | L61: =A61&"-"&B61&" x"&C61 | M61: =IFERROR(ROUND((F61-G61)/F61,4),0) | N61: =UPPER(LEFT(B61,3))&MOD(C61,7) | O61: =SUMIFS($C$2:$C$201,$A$2:$A$201,A61,$B$2:$B$201,B61) | P61: =VLOOKUP(B61,Products!$A$2:$B$6,2,FALSE) | Q61: =Q60+F61
A62: South | B62: Gadget | C62: 52 | D62: 44.49 | F62: =C62*D62*(1-E62) | G62: =F62*TaxRate | H62: =IF(F62>=Assumptions!$B$2,"High",IF(F62>=Assumptions!$B$2/5,"Mid","Low")) | I62: =F62/SUM($F$2:$F$201) | J62: =SUMIF($A$2:$A$201,A62,$F$2:$F$201) | K62: =F62/J62 | L62: =A62&"-"&B62&" x"&C62 | M62: =IFERROR(ROUND((F62-G62)/F62,4),0) | N62: =UPPER(LEFT(B62,3))&MOD(C62,7) | O62: =SUMIFS($C$2:$C$201,$A$2:$A$201,A62,$B$2:$B$201,B62) | P62: =VLOOKUP(B62,Products!$A$2:$B$6,2,FALSE) | Q62: =Q61+F62
A63: North | B63: Gadget | C63: 18 | D63: 40.01 | E63: 0.15 | F63: =C63*D63*(1-E63) | G63: =F63*TaxRate | H63: =IF(F63>=Assumptions!$B$2,"High",IF(F63>=Assumptions!$B$2/5,"Mid","Low")) | I63: =F63/SUM($F$2:$F$201) | J63: =SUMIF($A$2:$A$201,A63,$F$2:$F$201) | K63: =F63/J63 | L63: =A63&"-"&B63&" x"&C63 | M63: =IFERROR(ROUND((F63-G63)/F63,4),0) | N63: =UPPER(LEFT(B63,3))&MOD(C63,7) | O63: =SUMIFS($C$2:$C$201,$A$2:$A$201,A63,$B$2:$B$201,B63) | P63: =VLOOKUP(B63,Products!$A$2:$B$6,2,FALSE) | Q63: =Q62+F63
A64: North | B64: Gizmo | C64: 34 | D64: 7.07 | E64: 0 | F64: =C64*D64*(1-E64) | G64: =F64*TaxRate | H64: =IF(F64>=Assumptions!$B$2,"High",IF(F64>=Assumptions!$B$2/5,"Mid","Low")) | I64: =F64/SUM($F$2:$F$201) | J64: =SUMIF($A$2:$A$201,A64,$F$2:$F$201) | K64: =F64/J64 | L64: =A64&"-"&B64&" x"&C64 | M64: =IFERROR(ROUND((F64-G64)/F64,4),0) | N64: =UPPER(LEFT(B64,3))&MOD(C64,7) | O64: =SUMIFS($C$2:$C$201,$A$2:$A$201,A64,$B$2:$B$201,B64) | P64: =VLOOKUP(B64,Products!$A$2:$B$6,2,FALSE) | Q64: =Q63+F64
A65: East | B65: Gizmo | C65: 57 | D65: 7.16 | E65: 0.15 | F65: =C65*D65*(1-E65) | G65: =F65*TaxRate | H65: =IF(F65>=Assumptions!$B$2,"High",IF(F65>=Assumptions!$B$2/5,"Mid","Low")) | I65: =F65/SUM($F$2:$F$201) | J65: =SUMIF($A$2:$A$201,A65,$F$2:$F$201) | K65: =F65/J65 | L65: =A65&"-"&B65&" x"&C65 | M65: =IFERROR(ROUND((F65-G65)/F65,4),0) | N65: =UPPER(LEFT(B65,3))&MOD(C65,7) | O65: =SUMIFS($C$2:$C$201,$A$2:$A$201,A65,$B$2:$B$201,B65) | P65: =VLOOKUP(B65,Products!$A$2:$B$6,2,FALSE) | Q65: =Q64+F65
A66: Central | B66: Doohickey | C66: 52 | D66: 111.41 | E66: 0.15 | F66: =C66*D66*(1-E66) | G66: =F66*TaxRate | H66: =IF(F66>=Assumptions!$B$2,"High",IF(F66>=Assumptions!$B$2/5,"Mid","Low")) | I66: =F66/SUM($F$2:$F$201) | J66: =SUMIF($A$2:$A$201,A66,$F$2:$F$201) | K66: =F66/J66 | L66: =A66&"-"&B66&" x"&C66 | M66: =IFERROR(ROUND((F66-G66)/F66,4),0) | N66: =UPPER(LEFT(B66,3))&MOD(C66,7) | O66: =SUMIFS($C$2:$C$201,$A$2:$A$201,A66,$B$2:$B$201,B66) | P66: =VLOOKUP(B66,Products!$A$2:$B$6,2,FALSE) | Q66: =Q65+F66
A67: West | B67: Sprocket | C67: 9 | D67: 3.12 | F67: =C67*D67*(1-E67) | G67: =F67*TaxRate | H67: =IF(F67>=Assumptions!$B$2,"High",IF(F67>=Assumptions!$B$2/5,"Mid","Low")) | I67: =F67/SUM($F$2:$F$201) | J67: =SUMIF($A$2:$A$201,A67,$F$2:$F$201) | K67: =F67/J67 | L67: =A67&"-"&B67&" x"&C67 | M67: =IFERROR(ROUND((F67-G67)/F67,4),0) | N67: =UPPER(LEFT(B67,3))&MOD(C67,7) | O67: =SUMIFS($C$2:$C$201,$A$2:$A$201,A67,$B$2:$B$201,B67) | P67: =VLOOKUP(B67,Products!$A$2:$B$6,2,FALSE) | Q67: =Q66+F67
A68: South | B68: Gadget | C68: 38 | D68: 34.05 | E68: 0 | F68: =C68*D68*(1-E68) | G68: =F68*TaxRate | H68: =IF(F68>=Assumptions!$B$2,"High",IF(F68>=Assumptions!$B$2/5,"Mid","Low")) | I68: =F68/SUM($F$2:$F$201) | J68: =SUMIF($A$2:$A$201,A68,$F$2:$F$201) | K68: =F68/J68 | L68: =A68&"-"&B68&" x"&C68 | M68: =IFERROR(ROUND((F68-G68)/F68,4),0) | N68: =UPPER(LEFT(B68,3))&MOD(C68,7) | O68: =SUMIFS($C$2:$C$201,$A$2:$A$201,A68,$B$2:$B$201,B68) | P68: =VLOOKUP(B68,Products!$A$2:$B$6,2,FALSE) | Q68: =Q67+F68
A69: West | B69: Gadget | C69: 30 | D69: 41.43 | F69: =C69*D69*(1-E69) | G69: =F69*TaxRate | H69: =IF(F69>=Assumptions!$B$2,"High",IF(F69>=Assumptions!$B$2/5,"Mid","Low")) | I69: =F69/SUM($F$2:$F$201) | J69: =SUMIF($A$2:$A$201,A69,$F$2:$F$201) | K69: =F69/J69 | L69: =A69&"-"&B69&" x"&C69 | M69: =IFERROR(ROUND((F69-G69)/F69,4),0) | N69: =UPPER(LEFT(B69,3))&MOD(C69,7) | O69: =SUMIFS($C$2:$C$201,$A$2:$A$201,A69,$B$2:$B$201,B69) | P69: =VLOOKUP(B69,Products!$A$2:$B$6,2,FALSE) | Q69: =Q68+F69
A70: Central | B70: Widget | C70: 20 | D70: 13.18 | E70: 0.15 | F70: =C70*D70*(1-E70) | G70: =F70*TaxRate | H70: =IF(F70>=Assumptions!$B$2,"High",IF(F70>=Assumptions!$B$2/5,"Mid","Low")) | I70: =F70/SUM($F$2:$F$201) | J70: =SUMIF($A$2:$A$201,A70,$F$2:$F$201) | K70: =F70/J70 | L70: =A70&"-"&B70&" x"&C70 | M70: =IFERROR(ROUND((F70-G70)/F70,4),0) | N70: =UPPER(LEFT(B70,3))&MOD(C70,7) | O70: =SUMIFS($C$2:$C$201,$A$2:$A$201,A70,$B$2:$B$201,B70) | P70: =VLOOKUP(B70,Products!$A$2:$B$6,2,FALSE) | Q70: =Q69+F70
A71: Central | B71: Doohickey | C71: 50 | D71: 107.21 | E71: 0.15 | F71: =C71*D71*(1-E71) | G71: =F71*TaxRate | H71: =IF(F71>=Assumptions!$B$2,"High",IF(F71>=Assumptions!$B$2/5,"Mid","Low")) | I71: =F71/SUM($F$2:$F$201) | J71: =SUMIF($A$2:$A$201,A71,$F$2:$F$201) | K71: =F71/J71 | L71: =A71&"-"&B71&" x"&C71 | M71: =IFERROR(ROUND((F71-G71)/F71,4),0) | N71: =UPPER(LEFT(B71,3))&MOD(C71,7) | O71: =SUMIFS($C$2:$C$201,$A$2:$A$201,A71,$B$2:$B$201,B71) | P71: =VLOOKUP(B71,Products!$A$2:$B$6,2,FALSE) | Q71: =Q70+F71
A72: East | B72: Gadget | C72: 12 | D72: 37.32 | F72: =C72*D72*(1-E72) | G72: =F72*TaxRate | H72: =IF(F72>=Assumptions!$B$2,"High",IF(F72>=Assumptions!$B$2/5,"Mid","Low")) | I72: =F72/SUM($F$2:$F$201) | J72: =SUMIF($A$2:$A$201,A72,$F$2:$F$201) | K72: =F72/J72 | L72: =A72&"-"&B72&" x"&C72 | M72: =IFERROR(ROUND((F72-G72)/F72,4),0) | N72: =UPPER(LEFT(B72,3))&MOD(C72,7) | O72: =SUMIFS($C$2:$C$201,$A$2:$A$201,A72,$B$2:$B$201,B72) | P72: =VLOOKUP(B72,Products!$A$2:$B$6,2,FALSE) | Q72: =Q71+F72
A73: Central | B73: Doohickey | C73: 35 | D73: 84.98 | F73: =C73*D73*(1-E73) | G73: =F73*TaxRate | H73: =IF(F73>=Assumptions!$B$2,"High",IF(F73>=Assumptions!$B$2/5,"Mid","Low")) | I73: =F73/SUM($F$2:$F$201) | J73: =SUMIF($A$2:$A$201,A73,$F$2:$F$201) | K73: =F73/J73 | L73: =A73&"-"&B73&" x"&C73 | M73: =IFERROR(ROUND((F73-G73)/F73,4),0) | N73: =UPPER(LEFT(B73,3))&MOD(C73,7) | O73: =SUMIFS($C$2:$C$201,$A$2:$A$201,A73,$B$2:$B$201,B73) | P73: =VLOOKUP(B73,Products!$A$2:$B$6,2,FALSE) | Q73: =Q72+F73
A74: South | B74: Gizmo | C74: 39 | D74: 8.28 | E74: 0.15 | F74: =C74*D74*(1-E74) | G74: =F74*TaxRate | H74: =IF(F74>=Assumptions!$B$2,"High",IF(F74>=Assumptions!$B$2/5,"Mid","Low")) | I74: =F74/SUM($F$2:$F$201) | J74: =SUMIF($A$2:$A$201,A74,$F$2:$F$201) | K74: =F74/J74 | L74: =A74&"-"&B74&" x"&C74 | M74: =IFERROR(ROUND((F74-G74)/F74,4),0) | N74: =UPPER(LEFT(B74,3))&MOD(C74,7) | O74: =SUMIFS($C$2:$C$201,$A$2:$A$201,A74,$B$2:$B$201,B74) | P74: =VLOOKUP(B74,Products!$A$2:$B$6,2,FALSE) | Q74: =Q73+F74
A75: Central | B75: Gadget | C75: 44 | D75: 37.33 | E75: 0.15 | F75: =C75*D75*(1-E75) | G75: =F75*TaxRate | H75: =IF(F75>=Assumptions!$B$2,"High",IF(F75>=Assumptions!$B$2/5,"Mid","Low")) | I75: =F75/SUM($F$2:$F$201) | J75: =SUMIF($A$2:$A$201,A75,$F$2:$F$201) | K75: =F75/J75 | L75: =A75&"-"&B75&" x"&C75 | M75: =IFERROR(ROUND((F75-G75)/F75,4),0) | N75: =UPPER(LEFT(B75,3))&MOD(C75,7) | O75: =SUMIFS($C$2:$C$201,$A$2:$A$201,A75,$B$2:$B$201,B75) | P75: =VLOOKUP(B75,Products!$A$2:$B$6,2,FALSE) | Q75: =Q74+F75
A76: Central | B76: Doohickey | C76: 32 | D76: 112.11 | E76: 0.15 | F76: =C76*D76*(1-E76) | G76: =F76*TaxRate | H76: =IF(F76>=Assumptions!$B$2,"High",IF(F76>=Assumptions!$B$2/5,"Mid","Low")) | I76: =F76/SUM($F$2:$F$201) | J76: =SUMIF($A$2:$A$201,A76,$F$2:$F$201) | K76: =F76/J76 | L76: =A76&"-"&B76&" x"&C76 | M76: =IFERROR(ROUND((F76-G76)/F76,4),0) | N76: =UPPER(LEFT(B76,3))&MOD(C76,7) | O76: =SUMIFS($C$2:$C$201,$A$2:$A$201,A76,$B$2:$B$201,B76) | P76: =VLOOKUP(B76,Products!$A$2:$B$6,2,FALSE) | Q76: =Q75+F76
A77: North | B77: Sprocket | C77: 57 | D77: 3.51 | E77: 0.1 | F77: =C77*D77*(1-E77) | G77: =F77*TaxRate | H77: =IF(F77>=Assumptions!$B$2,"High",IF(F77>=Assumptions!$B$2/5,"Mid","Low")) | I77: =F77/SUM($F$2:$F$201) | J77: =SUMIF($A$2:$A$201,A77,$F$2:$F$201) | K77: =F77/J77 | L77: =A77&"-"&B77&" x"&C77 | M77: =IFERROR(ROUND((F77-G77)/F77,4),0) | N77: =UPPER(LEFT(B77,3))&MOD(C77,7) | O77: =SUMIFS($C$2:$C$201,$A$2:$A$201,A77,$B$2:$B$201,B77) | P77: =VLOOKUP(B77,Products!$A$2:$B$6,2,FALSE) | Q77: =Q76+F77
A78: West | B78: Doohickey | C78: 7 | D78: 95.8 | E78: 0.05 | F78: =C78*D78*(1-E78) | G78: =F78*TaxRate | H78: =IF(F78>=Assumptions!$B$2,"High",IF(F78>=Assumptions!$B$2/5,"Mid","Low")) | I78: =F78/SUM($F$2:$F$201) | J78: =SUMIF($A$2:$A$201,A78,$F$2:$F$201) | K78: =F78/J78 | L78: =A78&"-"&B78&" x"&C78 | M78: =IFERROR(ROUND((F78-G78)/F78,4),0) | N78: =UPPER(LEFT(B78,3))&MOD(C78,7) | O78: =SUMIFS($C$2:$C$201,$A$2:$A$201,A78,$B$2:$B$201,B78) | P78: =VLOOKUP(B78,Products!$A$2:$B$6,2,FALSE) | Q78: =Q77+F78
A79: East | B79: Gadget | C79: 27 | D79: 34.88 | E79: 0.05 | F79: =C79*D79*(1-E79) | G79: =F79*TaxRate | H79: =IF(F79>=Assumptions!$B$2,"High",IF(F79>=Assumptions!$B$2/5,"Mid","Low")) | I79: =F79/SUM($F$2:$F$201) | J79: =SUMIF($A$2:$A$201,A79,$F$2:$F$201) | K79: =F79/J79 | L79: =A79&"-"&B79&" x"&C79 | M79: =IFERROR(ROUND((F79-G79)/F79,4),0) | N79: =UPPER(LEFT(B79,3))&MOD(C79,7) | O79: =SUMIFS($C$2:$C$201,$A$2:$A$201,A79,$B$2:$B$201,B79) | P79: =VLOOKUP(B79,Products!$A$2:$B$6,2,FALSE) | Q79: =Q78+F79
A80: East | B80: Gadget | C80: 60 | D80: 42.59 | E80: 0.05 | F80: =C80*D80*(1-E80) | G80: =F80*TaxRate | H80: =IF(F80>=Assumptions!$B$2,"High",IF(F80>=Assumptions!$B$2/5,"Mid","Low")) | I80: =F80/SUM($F$2:$F$201) | J80: =SUMIF($A$2:$A$201,A80,$F$2:$F$201) | K80: =F80/J80 | L80: =A80&"-"&B80&" x"&C80 | M80: =IFERROR(ROUND((F80-G80)/F80,4),0) | N80: =UPPER(LEFT(B80,3))&MOD(C80,7) | O80: =SUMIFS($C$2:$C$201,$A$2:$A$201,A80,$B$2:$B$201,B80) | P80: =VLOOKUP(B80,Products!$A$2:$B$6,2,FALSE) | Q80: =Q79+F80
A81: West | B81: Gizmo | C81: 56 | D81: 6.46 | E81: 0.1 | F81: =C81*D81*(1-E81) | G81: =F81*TaxRate | H81: =IF(F81>=Assumptions!$B$2,"High",IF(F81>=Assumptions!$B$2/5,"Mid","Low")) | I81: =F81/SUM($F$2:$F$201) | J81: =SUMIF($A$2:$A$201,A81,$F$2:$F$201) | K81: =F81/J81 | L81: =A81&"-"&B81&" x"&C81 | M81: =IFERROR(ROUND((F81-G81)/F81,4),0) | N81: =UPPER(LEFT(B81,3))&MOD(C81,7) | O81: =SUMIFS($C$2:$C$201,$A$2:$A$201,A81,$B$2:$B$201,B81) | P81: =VLOOKUP(B81,Products!$A$2:$B$6,2,FALSE) | Q81: =Q80+F81
A82: West | B82: Widget | C82: 25 | D82: 13.94 | E82: 0 | F82: =C82*D82*(1-E82) | G82: =F82*TaxRate | H82: =IF(F82>=Assumptions!$B$2,"High",IF(F82>=Assumptions!$B$2/5,"Mid","Low")) | I82: =F82/SUM($F$2:$F$201) | J82: =SUMIF($A$2:$A$201,A82,$F$2:$F$201) | K82: =F82/J82 | L82: =A82&"-"&B82&" x"&C82 | M82: =IFERROR(ROUND((F82-G82)/F82,4),0) | N82: =UPPER(LEFT(B82,3))&MOD(C82,7) | O82: =SUMIFS($C$2:$C$201,$A$2:$A$201,A82,$B$2:$B$201,B82) | P82: =VLOOKUP(B82,Products!$A$2:$B$6,2,FALSE) | Q82: =Q81+F82
A83: West | B83: Gadget | C83: 45 | D83: 39.18 | E83: 0.15 | F83: =C83*D83*(1-E83) | G83: =F83*TaxRate | H83: =IF(F83>=Assumptions!$B$2,"High",IF(F83>=Assumptions!$B$2/5,"Mid","Low")) | I83: =F83/SUM($F$2:$F$201) | J83: =SUMIF($A$2:$A$201,A83,$F$2:$F$201) | K83: =F83/J83 | L83: =A83&"-"&B83&" x"&C83 | M83: =IFERROR(ROUND((F83-G83)/F83,4),0) | N83: =UPPER(LEFT(B83,3))&MOD(C83,7) | O83: =SUMIFS($C$2:$C$201,$A$2:$A$201,A83,$B$2:$B$201,B83) | P83: =VLOOKUP(B83,Products!$A$2:$B$6,2,FALSE) | Q83: =Q82+F83
A84: South | B84: Gizmo | C84: 26 | D84: 6.59 | E84: 0.05 | F84: =C84*D84*(1-E84) | G84: =F84*TaxRate | H84: =IF(F84>=Assumptions!$B$2,"High",IF(F84>=Assumptions!$B$2/5,"Mid","Low")) | I84: =F84/SUM($F$2:$F$201) | J84: =SUMIF($A$2:$A$201,A84,$F$2:$F$201) | K84: =F84/J84 | L84: =A84&"-"&B84&" x"&C84 | M84: =IFERROR(ROUND((F84-G84)/F84,4),0) | N84: =UPPER(LEFT(B84,3))&MOD(C84,7) | O84: =SUMIFS($C$2:$C$201,$A$2:$A$201,A84,$B$2:$B$201,B84) | P84: =VLOOKUP(B84,Products!$A$2:$B$6,2,FALSE) | Q84: =Q83+F84
A85: East | B85: Gizmo | C85: 1 | D85: 6.9 | E85: 0.1 | F85: =C85*D85*(1-E85) | G85: =F85*TaxRate | H85: =IF(F85>=Assumptions!$B$2,"High",IF(F85>=Assumptions!$B$2/5,"Mid","Low")) | I85: =F85/SUM($F$2:$F$201) | J85: =SUMIF($A$2:$A$201,A85,$F$2:$F$201) | K85: =F85/J85 | L85: =A85&"-"&B85&" x"&C85 | M85: =IFERROR(ROUND((F85-G85)/F85,4),0) | N85: =UPPER(LEFT(B85,3))&MOD(C85,7) | O85: =SUMIFS($C$2:$C$201,$A$2:$A$201,A85,$B$2:$B$201,B85) | P85: =VLOOKUP(B85,Products!$A$2:$B$6,2,FALSE) | Q85: =Q84+F85
... A91: South | B91: Gizmo | C91: 5 | D91: 6.77 | E91: 0 | F91: =C91*D91*(1-E91) | G91: =F91*TaxRate | H91: =IF(F91>=Assumptions!$B$2,"High",IF(F91>=Assumptions!$B$2/5,"Mid","Low")) | I91: =F91/SUM($F$2:$F$201) | J91: =SUMIF($A$2:$A$201,A91,$F$2:$F$201) | K91: =F91/J91 | L91: =A91&"-"&B91&" x"&C91 | M91: =IFERROR(ROUND((F91-G91)/F91,4),0) | N91: =UPPER(LEFT(B91,3))&MOD(C91,7) | O91: =SUMIFS($C$2:$C$201,$A$2:$A$201,A91,$B$2:$B$201,B91) | P91: =VLOOKUP(B91,Products!$A$2:$B$6,2,FALSE) | Q91: =Q90+F91
A92: South | B92: Widget | C92: 17 | D92: 14.14 | F92: =C92*D92*(1-E92) | G92: =F92*TaxRate | H92: =IF(F92>=Assumptions!$B$2,"High",IF(F92>=Assumptions!$B$2/5,"Mid","Low")) | I92: =F92/SUM($F$2:$F$201) | J92: =SUMIF($A$2:$A$201,A92,$F$2:$F$201) | K92: =F92/J92 | L92: =A92&"-"&B92&" x"&C92 | M92: =IFERROR(ROUND((F92-G92)/F92,4),0) | N92: =UPPER(LEFT(B92,3))&MOD(C92,7) | O92: =SUMIFS($C$2:$C$201,$A$2:$A$201,A92,$B$2:$B$201,B92) | P92: =VLOOKUP(B92,Products!$A$2:$B$6,2,FALSE) | Q92: =Q91+F92
A93: North | B93: Widget | C93: 38 | D93: 13.84 | F93: =C93*D93*(1-E93) | G93: =F93*TaxRate | H93: =IF(F93>=Assumptions!$B$2,"High",IF(F93>=Assumptions!$B$2/5,"Mid","Low")) | I93: =F93/SUM($F$2:$F$201) | J93: =SUMIF($A$2:$A$201,A93,$F$2:$F$201) | K93: =F93/J93 | L93: =A93&"-"&B93&" x"&C93 | M93: =IFERROR(ROUND((F93-G93)/F93,4),0) | N93: =UPPER(LEFT(B93,3))&MOD(C93,7) | O93: =SUMIFS($C$2:$C$201,$A$2:$A$201,A93,$B$2:$B$201,B93) | P93: =VLOOKUP(B93,Products!$A$2:$B$6,2,FALSE) | Q93: =Q92+F93
A94: North | B94: Widget | C94: 29 | D94: 10.67 | E94: 0.15 | F94: =C94*D94*(1-E94) | G94: =F94*TaxRate | H94: =IF(F94>=Assumptions!$B$2,"High",IF(F94>=Assumptions!$B$2/5,"Mid","Low")) | I94: =F94/SUM($F$2:$F$201) | J94: =SUMIF($A$2:$A$201,A94,$F$2:$F$201) | K94: =F94/J94 | L94: =A94&"-"&B94&" x"&C94 | M94: =IFERROR(ROUND((F94-G94)/F94,4),0) | N94: =UPPER(LEFT(B94,3))&MOD(C94,7) | O94: =SUMIFS($C$2:$C$201,$A$2:$A$201,A94,$B$2:$B$201,B94) | P94: =VLOOKUP(B94,Products!$A$2:$B$6,2,FALSE) | Q94: =Q93+F94
A95: South | B95: Gizmo | C95: 39 | D95: 6.44 | E95: 0.15 | F95: =C95*D95*(1-E95) | G95: =F95*TaxRate | H95: =IF(F95>=Assumptions!$B$2,"High",IF(F95>=Assumptions!$B$2/5,"Mid","Low")) | I95: =F95/SUM($F$2:$F$201) | J95: =SUMIF($A$2:$A$201,A95,$F$2:$F$201) | K95: =F95/J95 | L95: =A95&"-"&B95&" x"&C95 | M95: =IFERROR(ROUND((F95-G95)/F95,4),0) | N95: =UPPER(LEFT(B95,3))&MOD(C95,7) | O95: =SUMIFS($C$2:$C$201,$A$2:$A$201,A95,$B$2:$B$201,B95) | P95: =VLOOKUP(B95,Products!$A$2:$B$6,2,FALSE) | Q95: =Q94+F95
A96: West | B96: Widget | C96: 10 | D96: 11.61 | E96: 0 | F96: =C96*D96*(1-E96) | G96: =F96*TaxRate | H96: =IF(F96>=Assumptions!$B$2,"High",IF(F96>=Assumptions!$B$2/5,"Mid","Low")) | I96: =F96/SUM($F$2:$F$201) | J96: =SUMIF($A$2:$A$201,A96,$F$2:$F$201) | K96: =F96/J96 | L96: =A96&"-"&B96&" x"&C96 | M96: =IFERROR(ROUND((F96-G96)/F96,4),0) | N96: =UPPER(LEFT(B96,3))&MOD(C96,7) | O96: =SUMIFS($C$2:$C$201,$A$2:$A$201,A96,$B$2:$B$201,B96) | P96: =VLOOKUP(B96,Products!$A$2:$B$6,2,FALSE) | Q96: =Q95+F96
A97: West | B97: Gizmo | C97: 40 | D97: 6.83 | E97: 0 | F97: =C97*D97*(1-E97) | G97: =F97*TaxRate | H97: =IF(F97>=Assumptions!$B$2,"High",IF(F97>=Assumptions!$B$2/5,"Mid","Low")) | I97: =F97/SUM($F$2:$F$201) | J97: =SUMIF($A$2:$A$201,A97,$F$2:$F$201) | K97: =F97/J97 | L97: =A97&"-"&B97&" x"&C97 | M97: =IFERROR(ROUND((F97-G97)/F97,4),0) | N97: =UPPER(LEFT(B97,3))&MOD(C97,7) | O97: =SUMIFS($C$2:$C$201,$A$2:$A$201,A97,$B$2:$B$201,B97) | P97: =VLOOKUP(B97,Products!$A$2:$B$6,2,FALSE) | Q97: =Q96+F97
A98: North | B98: Doohickey | C98: 32 | D98: 104.11 | E98: 0.05 | F98: =C98*D98*(1-E98) | G98: =F98*TaxRate | H98: =IF(F98>=Assumptions!$B$2,"High",IF(F98>=Assumptions!$B$2/5,"Mid","Low")) | I98: =F98/SUM($F$2:$F$201) | J98: =SUMIF($A$2:$A$201,A98,$F$2:$F$201) | K98: =F98/J98 | L98: =A98&"-"&B98&" x"&C98 | M98: =IFERROR(ROUND((F98-G98)/F98,4),0) | N98: =UPPER(LEFT(B98,3))&MOD(C98,7) | O98: =SUMIFS($C$2:$C$201,$A$2:$A$201,A98,$B$2:$B$201,B98) | P98: =VLOOKUP(B98,Products!$A$2:$B$6,2,FALSE) | Q98: =Q97+F98
A99: North | B99: Widget | C99: 16 | D99: 10.76 | F99: =C99*D99*(1-E99) | G99: =F99*TaxRate | H99: =IF(F99>=Assumptions!$B$2,"High",IF(F99>=Assumptions!$B$2/5,"Mid","Low")) | I99: =F99/SUM($F$2:$F$201) | J99: =SUMIF($A$2:$A$201,A99,$F$2:$F$201) | K99: =F99/J99 | L99: =A99&"-"&B99&" x"&C99 | M99: =IFERROR(ROUND((F99-G99)/F99,4),0) | N99: =UPPER(LEFT(B99,3))&MOD(C99,7) | O99: =SUMIFS($C$2:$C$201,$A$2:$A$201,A99,$B$2:$B$201,B99) | P99: =VLOOKUP(B99,Products!$A$2:$B$6,2,FALSE) | Q99: =Q98+F99
A100: Central | B100: Sprocket | C100: 12 | D100: 3.11 | E100: 0 | F100: =C100*D100*(1-E100) | G100: =F100*TaxRate | H100: =IF(F100>=Assumptions!$B$2,"High",IF(F100>=Assumptions!$B$2/5,"Mid","Low")) | I100: =F100/SUM($F$2:$F$201) | J100: =SUMIF($A$2:$A$201,A100,$F$2:$F$201) | K100: =F100/J100 | L100: =A100&"-"&B100&" x"&C100 | M100: =IFERROR(ROUND((F100-G100)/F100,4),0) | N100: =UPPER(LEFT(B100,3))&MOD(C100,7) | O100: =SUMIFS($C$2:$C$201,$A$2:$A$201,A100,$B$2:$B$201,B100) | P100: =VLOOKUP(B100,Products!$A$2:$B$6,2,FALSE) | Q100: =Q99+F100
A101: South | B101: Widget | C101: 42 | D101: 13.7 | E101: 0.1 | F101: =C101*D101*(1-E101) | G101: =F101*TaxRate | H101: =IF(F101>=Assumptions!$B$2,"High",IF(F101>=Assumptions!$B$2/5,"Mid","Low")) | I101: =F101/SUM($F$2:$F$201) | J101: =SUMIF($A$2:$A$201,A101,$F$2:$F$201) | K101: =F101/J101 | L101: =A101&"-"&B101&" x"&C101 | M101: =IFERROR(ROUND((F101-G101)/F101,4),0) | N101: =UPPER(LEFT(B101,3))&MOD(C101,7) | O101: =SUMIFS($C$2:$C$201,$A$2:$A$201,A101,$B$2:$B$201,B101) | P101: =VLOOKUP(B101,Products!$A$2:$B$6,2,FALSE) | Q101: =Q100+F101
A102: South | B102: Sprocket | C102: 53 | D102: 3.46 | E102: 0.15 | F102: =C102*D102*(1-E102) | G102: =F102*TaxRate | H102: =IF(F102>=Assumptions!$B$2,"High",IF(F102>=Assumptions!$B$2/5,"Mid","Low")) | I102: =F102/SUM($F$2:$F$201) | J102: =SUMIF($A$2:$A$201,A102,$F$2:$F$201) | K102: =F102/J102 | L102: =A102&"-"&B102&" x"&C102 | M102: =IFERROR(ROUND((F102-G102)/F102,4),0) | N102: =UPPER(LEFT(B102,3))&MOD(C102,7) | O102: =SUMIFS($C$2:$C$201,$A$2:$A$201,A102,$B$2:$B$201,B102) | P102: =VLOOKUP(B102,Products!$A$2:$B$6,2,FALSE) | Q102: =Q101+F102
A103: North | B103: Gadget | C103: 14 | D103: 38.11 | E103: 0 | F103: =C103*D103*(1-E103) | G103: =F103*TaxRate | H103: =IF(F103>=Assumptions!$B$2,"High",IF(F103>=Assumptions!$B$2/5,"Mid","Low")) | I103: =F103/SUM($F$2:$F$201) | J103: =SUMIF($A$2:$A$201,A103,$F$2:$F$201) | K103: =F103/J103 | L103: =A103&"-"&B103&" x"&C103 | M103: =IFERROR(ROUND((F103-G103)/F103,4),0) | N103: =UPPER(LEFT(B103,3))&MOD(C103,7) | O103: =SUMIFS($C$2:$C$201,$A$2:$A$201,A103,$B$2:$B$201,B103) | P103: =VLOOKUP(B103,Products!$A$2:$B$6,2,FALSE) | Q103: =Q102+F103
A104: South | B104: Gizmo | C104: 3 | D104: 7.98 | F104: =C104*D104*(1-E104) | G104: =F104*TaxRate | H104: =IF(F104>=Assumptions!$B$2,"High",IF(F104>=Assumptions!$B$2/5,"Mid","Low")) | I104: =F104/SUM($F$2:$F$201) | J104: =SUMIF($A$2:$A$201,A104,$F$2:$F$201) | K104: =F104/J104 | L104: =A104&"-"&B104&" x"&C104 | M104: =IFERROR(ROUND((F104-G104)/F104,4),0) | N104: =UPPER(LEFT(B104,3))&MOD(C104,7) | O104: =SUMIFS($C$2:$C$201,$A$2:$A$201,A104,$B$2:$B$201,B104) | P104: =VLOOKUP(B104,Products!$A$2:$B$6,2,FALSE) | Q104: =Q103+F104
A105: East | B105: Gizmo | C105: 27 | D105: 6.52 | F105: =C105*D105*(1-E105) | G105: =F105*TaxRate | H105: =IF(F105>=Assumptions!$B$2,"High",IF(F105>=Assumptions!$B$2/5,"Mid","Low")) | I105: =F105/SUM($F$2:$F$201) | J105: =SUMIF($A$2:$A$201,A105,$F$2:$F$201) | K105: =F105/J105 | L105: =A105&"-"&B105&" x"&C105 | M105: =IFERROR(ROUND((F105-G105)/F105,4),0) | N105: =UPPER(LEFT(B105,3))&MOD(C105,7) | O105: =SUMIFS($C$2:$C$201,$A$2:$A$201,A105,$B$2:$B$201,B105) | P105: =VLOOKUP(B105,Products!$A$2:$B$6,2,FALSE) | Q105: =Q104+F105
...

Sheet Products
A1: Product | B1: List Price
A2: Widget | B2: 12.5
A3: Gadget | B3: 40
A4: Gizmo | B4: 7.25
A5: Doohickey | B5: 99
A6: Sprocket | B6: 3.1

Sheet Assumptions
A1: Tax Rate | B1: 0.0825
A2: High Threshold | B2: 1000
